bypasssafe/__init__.py
bypasssafe/account.py
bypasssafe/database.py
bypasssafe/main.py
bypasssafe/pass_gen.py
ByPassSafe2-0.1.dist-info/METADATA
ByPassSafe2-0.1.dist-info/WHEEL
ByPassSafe2-0.1.dist-info/entry_points.txt
ByPassSafe2-0.1.dist-info/top_level.txt
ByPassSafe2-0.1.dist-info/RECORD
