Metadata-Version: 2.1
Name: ByPassSafe2
Version: 0.1
Requires-Dist: psycopg2
Requires-Dist: bcrypt
